pharmaradar/__init__.py
pharmaradar/availability_level.py
pharmaradar/location_selector.py
pharmaradar/medicine.py
pharmaradar/medicine_scraper.py
pharmaradar/pharmacy_info.py
pharmaradar/scraping_utils.py
pharmaradar/text_parsers.py
pharmaradar/webdriver_utils.py
pharmaradar/database/database_interface.py
pharmaradar/service/medicine_watchdog.py
pharmaradar-1.2.2.dist-info/licenses/LICENSE
pharmaradar-1.2.2.dist-info/METADATA
pharmaradar-1.2.2.dist-info/WHEEL
pharmaradar-1.2.2.dist-info/top_level.txt
pharmaradar-1.2.2.dist-info/RECORD
