Metadata-Version: 2.4
Name: pharmaradar
Version: 1.2.2
Summary: Python scraping package for KtoMaLek.pl website to monitor drug availability.
Author: bartekmp
License-Expression: MIT
Keywords: ktomalek,pharmaradar,web scraping,selenium
Requires-Python: >=3.12
License-File: LICENSE
Requires-Dist: selenium>=4.15.0
Requires-Dist: lxml>=5.0.0
Provides-Extra: dev
Requires-Dist: pytest==9.0.2; extra == "dev"
Requires-Dist: pytest-mock==3.15.1; extra == "dev"
Requires-Dist: black==25.12.0; extra == "dev"
Requires-Dist: flake8==7.3.0; extra == "dev"
Requires-Dist: isort==7.0.0; extra == "dev"
Requires-Dist: python-semantic-release==10.5.3; extra == "dev"
Requires-Dist: build==1.3.0; extra == "dev"
Requires-Dist: twine==6.2.0; extra == "dev"
Dynamic: license-file
